sumochip/README.md
sumochip/__init__.py
sumochip/code.txt
sumochip/sumochip.service
sumochip/sumorobot.py
sumochip/webapp.py
sumochip/config/sumochip_v1.0.ini
sumochip/config/sumochip_v1.1.ini
sumochip/config/template.ini
sumochip/static/app.js
sumochip/static/basic.css
sumochip/static/blockly/blockly_compressed.js
sumochip/static/blockly/blocks_compressed.js
sumochip/static/blockly/en.js
sumochip/static/blockly/et.js
sumochip/static/blockly/javascript_compressed.js
sumochip/static/blockly/lua_compressed.js
sumochip/static/blockly/python_compressed.js
sumochip/static/blockly/generators/lua.js
sumochip/static/blockly/generators/lua/colour.js
sumochip/static/blockly/generators/lua/lists.js
sumochip/static/blockly/generators/lua/logic.js
sumochip/static/blockly/generators/lua/loops.js
sumochip/static/blockly/generators/lua/math.js
sumochip/static/blockly/generators/lua/procedures.js
sumochip/static/blockly/generators/lua/text.js
sumochip/static/blockly/generators/lua/variables.js
sumochip/static/blockly/media/1x1.gif
sumochip/static/blockly/media/click.mp3
sumochip/static/blockly/media/click.ogg
sumochip/static/blockly/media/click.wav
sumochip/static/blockly/media/delete.mp3
sumochip/static/blockly/media/delete.ogg
sumochip/static/blockly/media/delete.wav
sumochip/static/blockly/media/disconnect.mp3
sumochip/static/blockly/media/disconnect.ogg
sumochip/static/blockly/media/disconnect.wav
sumochip/static/blockly/media/handclosed.cur
sumochip/static/blockly/media/handdelete.cur
sumochip/static/blockly/media/handopen.cur
sumochip/static/blockly/media/quote0.png
sumochip/static/blockly/media/quote1.png
sumochip/static/blockly/media/sprites.png
sumochip/static/blockly/media/sprites.svg
sumochip/static/codemirror/codemirror.css
sumochip/static/codemirror/codemirror.html
sumochip/static/codemirror/codemirror.js
sumochip/static/codemirror/lua.js
sumochip/static/codemirror/python.js
sumochip/static/img/darr.png
sumochip-1.1.1.dist-info/DESCRIPTION.rst
sumochip-1.1.1.dist-info/METADATA
sumochip-1.1.1.dist-info/RECORD
sumochip-1.1.1.dist-info/WHEEL
sumochip-1.1.1.dist-info/entry_points.txt
sumochip-1.1.1.dist-info/metadata.json
sumochip-1.1.1.dist-info/top_level.txt
